{
  "legislative_session": "2026",
  "identifier": "SB3095",
  "title": "RELATING TO THE HAWAII EMPLOYER-UNION HEALTH BENEFITS TRUST FUND INVESTMENT OFFICE STAFF SALARIES.",
  "from_organization": "~{\"classification\": \"upper\"}",
  "classification": [
    "bill"
  ],
  "subject": [
    "Hawaii Employer-Union Health Benefits Trust Fund",
    "Investment Office Staff Salary Determination"
  ],
  "abstracts": [
    {
      "note": "description",
      "abstract": "Authorizes the Board of Trustees of the Hawaii Employer-Union Health Benefits Trust Fund to establish appropriate salaries for the investment officers and investment analysts of the Trust Fund.  Effective 7/1/3000.  (HD1)"
    }
  ],
  "other_titles": [],
  "other_identifiers": [
    {
      "identifier": "ocd-bill-hi-2026-sb3095"
    }
  ],
  "actions": [
    {
      "description": "Passed Second Reading as amended in HD 1 and referred to the committee(s) on FIN with Representative(s) Gedeon, Reyes Oda voting aye with reservations; Representative(s) Alcos, Garcia, Pierick voting no (3) and Representative(s) Garrett, Quinlan excused (2).",
      "date": "2026-03-24",
      "organization_id": "~{\"classification\": \"lower\"}",
      "classification": [
        "reading-2",
        "referral-committee"
      ],
      "related_entities": [
        {
          "name": "Finance",
          "entity_type": "organization",
          "organization_id": null
        }
      ],
      "_processing": {
        "log_file_created": "2026-07-13T06:04:09Z"
      }
    },
    {
      "description": "Reported from LAB (Stand. Com. Rep. No. 1367-26) as amended in HD 1, recommending passage on Second Reading and referral to FIN.",
      "date": "2026-03-24",
      "organization_id": "~{\"classification\": \"lower\"}",
      "classification": [],
      "related_entities": [],
      "_processing": {
        "log_file_created": "2026-07-13T06:04:09Z"
      }
    },
    {
      "description": "The committee on LAB recommend that the measure be PASSED, WITH AMENDMENTS. The votes were as follows: 6 Ayes: Representative(s) Sayama, Lee, M., Garrett, Kapela, Kong; Ayes with reservations: Representative(s) Reyes Oda; 0 Noes: none; and 0 Excused: none.",
      "date": "2026-03-19",
      "organization_id": "~{\"classification\": \"lower\"}",
      "classification": [
        "committee-passage-favorable"
      ],
      "related_entities": [],
      "_processing": {
        "log_file_created": "2026-07-13T06:04:09Z"
      }
    },
    {
      "description": "Bill scheduled to be heard by LAB on Thursday, 03-19-26 9:35AM in House conference room 309 VIA VIDEOCONFERENCE.",
      "date": "2026-03-16",
      "organization_id": "~{\"classification\": \"lower\"}",
      "classification": [],
      "related_entities": [],
      "_processing": {
        "log_file_created": "2026-07-13T06:04:09Z"
      }
    },
    {
      "description": "Referred to LAB, FIN, referral sheet 16",
      "date": "2026-03-10",
      "organization_id": "~{\"classification\": \"lower\"}",
      "classification": [
        "referral-committee"
      ],
      "related_entities": [
        {
          "name": "Labor",
          "entity_type": "organization",
          "organization_id": null
        },
        {
          "name": "Finance",
          "entity_type": "organization",
          "organization_id": null
        }
      ],
      "_processing": {
        "log_file_created": "2026-07-13T06:04:09Z"
      }
    },
    {
      "description": "Pass First Reading",
      "date": "2026-03-10",
      "organization_id": "~{\"classification\": \"lower\"}",
      "classification": [
        "reading-1"
      ],
      "related_entities": [],
      "_processing": {
        "log_file_created": "2026-07-13T06:04:09Z"
      }
    },
    {
      "description": "Received from Senate (Sen. Com. No. 107) in amended form (SD 1).",
      "date": "2026-03-06",
      "organization_id": "~{\"classification\": \"lower\"}",
      "classification": [
        "introduction",
        "receipt"
      ],
      "related_entities": [],
      "_processing": {
        "log_file_created": "2026-07-13T06:04:09Z"
      }
    },
    {
      "description": "Report Adopted; Passed Third Reading. Ayes, 21; Aye(s) with reservations: none.  Noes, 3 (Senator(s) Awa, DeCorte, Fevella).  Excused, 1 (Senator(s) Ihara).  Transmitted to House.",
      "date": "2026-03-06",
      "organization_id": "~{\"classification\": \"upper\"}",
      "classification": [
        "passage"
      ],
      "related_entities": [],
      "_processing": {
        "log_file_created": "2026-07-13T06:04:09Z"
      }
    },
    {
      "description": "One Day Notice 03-06-26.",
      "date": "2026-03-05",
      "organization_id": "~{\"classification\": \"upper\"}",
      "classification": [],
      "related_entities": [],
      "_processing": {
        "log_file_created": "2026-07-13T06:04:09Z"
      }
    },
    {
      "description": "Reported from WAM (Stand. Com. Rep. No. 2727) with recommendation of passage on Third Reading.",
      "date": "2026-03-05",
      "organization_id": "~{\"classification\": \"upper\"}",
      "classification": [],
      "related_entities": [],
      "_processing": {
        "log_file_created": "2026-07-13T06:04:09Z"
      }
    },
    {
      "description": "The committee(s) on WAM recommend(s) that the measure be PASSED, UNAMENDED.  The votes in WAM were as follows: 13 Aye(s): Senator(s) Dela Cruz, Moriwaki, DeCoite, Elefante, Hashimoto, Inouye, Kanuha, Kidani, Kim, Lee, C., Richards, Wakai, Fevella; Aye(s) with reservations: none ; 0 No(es): none; and 0 Excused: none.",
      "date": "2026-03-02",
      "organization_id": "~{\"classification\": \"upper\"}",
      "classification": [
        "committee-passage-favorable"
      ],
      "related_entities": [],
      "_processing": {
        "log_file_created": "2026-07-13T06:04:09Z"
      }
    },
    {
      "description": "The committee on WAM has rescheduled its decision making to 03-02-26 10:02AM; CR 211 & Videoconference.",
      "date": "2026-02-27",
      "organization_id": "~{\"classification\": \"upper\"}",
      "classification": [],
      "related_entities": [],
      "_processing": {
        "log_file_created": "2026-07-13T06:04:09Z"
      }
    },
    {
      "description": "The committee(s) on WAM will hold a public decision making on 03-02-26 10:31AM; Conference Room 211 & Videoconference.",
      "date": "2026-02-23",
      "organization_id": "~{\"classification\": \"upper\"}",
      "classification": [],
      "related_entities": [],
      "_processing": {
        "log_file_created": "2026-07-13T06:04:09Z"
      }
    },
    {
      "description": "Report adopted; Passed Second Reading, as amended (SD 1) and referred to WAM.",
      "date": "2026-02-20",
      "organization_id": "~{\"classification\": \"upper\"}",
      "classification": [
        "reading-2",
        "referral-committee"
      ],
      "related_entities": [
        {
          "name": "Ways and Means",
          "entity_type": "organization",
          "organization_id": null
        }
      ],
      "_processing": {
        "log_file_created": "2026-07-13T06:04:09Z"
      }
    },
    {
      "description": "Reported from LBT (Stand. Com. Rep. No. 2539) with recommendation of passage on Second Reading, as amended (SD 1) and referral to WAM.",
      "date": "2026-02-20",
      "organization_id": "~{\"classification\": \"upper\"}",
      "classification": [],
      "related_entities": [],
      "_processing": {
        "log_file_created": "2026-07-13T06:04:09Z"
      }
    },
    {
      "description": "The committee(s) on  LBT recommend(s) that the measure be PASSED, WITH AMENDMENTS.  The votes in LBT were as follows: 3 Aye(s): Senator(s) Elefante, Lamosao, Moriwaki; Aye(s) with reservations: none ; 0 No(es): none; and 2 Excused: Senator(s) Ihara, Fevella.",
      "date": "2026-02-18",
      "organization_id": "~{\"classification\": \"upper\"}",
      "classification": [
        "committee-passage-favorable"
      ],
      "related_entities": [],
      "_processing": {
        "log_file_created": "2026-07-13T06:04:09Z"
      }
    },
    {
      "description": "The committee(s) on LBT has scheduled a public hearing on 02-18-26 3:01PM; Conference Room 225 & Videoconference.",
      "date": "2026-02-13",
      "organization_id": "~{\"classification\": \"upper\"}",
      "classification": [],
      "related_entities": [],
      "_processing": {
        "log_file_created": "2026-07-13T06:04:09Z"
      }
    },
    {
      "description": "Referred to LBT, WAM.",
      "date": "2026-01-30",
      "organization_id": "~{\"classification\": \"upper\"}",
      "classification": [
        "referral-committee"
      ],
      "related_entities": [
        {
          "name": "Labor and Technology",
          "entity_type": "organization",
          "organization_id": null
        },
        {
          "name": "Ways and Means",
          "entity_type": "organization",
          "organization_id": null
        }
      ],
      "_processing": {
        "log_file_created": "2026-07-13T06:04:09Z"
      }
    },
    {
      "description": "Passed First Reading.",
      "date": "2026-01-28",
      "organization_id": "~{\"classification\": \"upper\"}",
      "classification": [
        "reading-1"
      ],
      "related_entities": [],
      "_processing": {
        "log_file_created": "2026-07-13T06:04:09Z"
      }
    },
    {
      "description": "Introduced.",
      "date": "2026-01-28",
      "organization_id": "~{\"classification\": \"upper\"}",
      "classification": [
        "introduction"
      ],
      "related_entities": [],
      "_processing": {
        "log_file_created": "2026-07-13T06:04:09Z"
      }
    },
    {
      "description": "Pending Introduction.",
      "date": "2026-01-26",
      "organization_id": "~{\"classification\": \"upper\"}",
      "classification": [],
      "related_entities": [],
      "_processing": {
        "log_file_created": "2026-07-13T06:04:09Z"
      }
    }
  ],
  "sponsorships": [
    {
      "name": "KOUCHI",
      "classification": "primary",
      "entity_type": "person",
      "primary": true,
      "person_id": "~{\"name\": \"KOUCHI\"}",
      "organization_id": null
    }
  ],
  "related_bills": [
    {
      "identifier": "HB 2276",
      "legislative_session": "2026 Regular Session",
      "relation_type": "companion"
    }
  ],
  "versions": [
    {
      "note": "SB3095_HD1",
      "links": [
        {
          "url": "https://data.capitol.hawaii.gov/sessions/session2026/bills/SB3095_HD1_.HTM",
          "media_type": "text/html"
        },
        {
          "url": "https://data.capitol.hawaii.gov/sessions/session2026/bills/SB3095_HD1_.PDF",
          "media_type": "application/pdf"
        }
      ],
      "date": "",
      "classification": ""
    },
    {
      "note": "SB3095",
      "links": [
        {
          "url": "https://data.capitol.hawaii.gov/sessions/session2026/bills/SB3095_.HTM",
          "media_type": "text/html"
        },
        {
          "url": "https://data.capitol.hawaii.gov/sessions/session2026/bills/SB3095_.PDF",
          "media_type": "application/pdf"
        }
      ],
      "date": "",
      "classification": ""
    },
    {
      "note": "SB3095_SD1",
      "links": [
        {
          "url": "https://data.capitol.hawaii.gov/sessions/session2026/bills/SB3095_SD1_.HTM",
          "media_type": "text/html"
        },
        {
          "url": "https://data.capitol.hawaii.gov/sessions/session2026/bills/SB3095_SD1_.PDF",
          "media_type": "application/pdf"
        }
      ],
      "date": "",
      "classification": ""
    }
  ],
  "documents": [],
  "citations": [],
  "sources": [
    {
      "url": "https://capitol.hawaii.gov/session/measure_indiv.aspx?billtype=SB&billnumber=3095&year=2026",
      "note": ""
    }
  ],
  "extras": {
    "current_referral": "LAB, FIN"
  },
  "jurisdiction": {
    "id": "ocd-jurisdiction/country:us/state:hi/government",
    "name": "Hawaii",
    "classification": "state",
    "division_id": "ocd-division/country:us/state:hi"
  },
  "_processing": {
    "logs_latest_update": "2026-07-13T06:04:09Z",
    "text_extraction_latest_update": "2026-07-13T18:05:00.779056Z"
  }
}