{
  "action": {
    "description": "Referred to LAB, FIN, referral sheet 18",
    "occurred_at": "2026-03-18",
    "jurisdiction_id": "~{\"classification\": \"lower\"}",
    "session_id": "2026",
    "entity_type": "bill",
    "classifications": [
      "referral-committee"
    ],
    "related_entities": [
      {
        "name": "Labor",
        "entity_type": "organization",
        "organization_id": null
      },
      {
        "name": "Finance",
        "entity_type": "organization",
        "organization_id": null
      }
    ],
    "sources": [
      {
        "url": "https://capitol.hawaii.gov/session/measure_indiv.aspx?billtype=HCR&billnumber=81&year=2026",
        "note": ""
      }
    ]
  },
  "bill_id": "HCR81"
}