{
  "action": {
    "description": "Act 190, 07/07/2026 (Gov. Msg. No. 1292).",
    "occurred_at": "2026-07-07",
    "jurisdiction_id": "~{\"classification\": \"upper\"}",
    "session_id": "2026",
    "entity_type": "bill",
    "classifications": [
      "became-law"
    ],
    "related_entities": [],
    "sources": [
      {
        "url": "https://capitol.hawaii.gov/session/measure_indiv.aspx?billtype=HB&billnumber=1573&year=2026",
        "note": ""
      }
    ]
  },
  "bill_id": "HB1573"
}