{
  "action": {
    "description": "The committee on FIN recommend that the measure be PASSED, WITH AMENDMENTS. The votes were as follows: 14 Ayes: Representative(s) Yamashita, Takenouchi, Grandinetti, Holt, Hussey, Keohokapu-Lee Loy, Kitagawa, Kusch, Lamosao, Lee, M., Miyake, Morikawa, Templo; Ayes with reservations: Representative(s) Reyes Oda; 1 Noes: Representative(s) Alcos; and 1 Excused: Representative(s) Ward.",
    "occurred_at": "2025-02-26",
    "jurisdiction_id": "~{\"classification\": \"lower\"}",
    "session_id": "2026",
    "entity_type": "bill",
    "classifications": [
      "committee-passage-favorable"
    ],
    "related_entities": [],
    "sources": [
      {
        "url": "https://capitol.hawaii.gov/session/measure_indiv.aspx?billtype=HB&billnumber=504&year=2026",
        "note": ""
      }
    ]
  },
  "bill_id": "HB504"
}