{
  "legislative_session": "2026",
  "identifier": "HCR77",
  "title": "REQUESTING THE DEPARTMENT OF EDUCATION AND THE UNIVERSITY OF HAWAII AT MANOA COLLEGE OF TROPICAL AGRICULTURE AND HUMAN RESILIENCE TO SUPPORT THE DEPARTMENT OF EDUCATION'S  SECONDARY AGRICULTURAL EDUCATION PROGRAM AND THE FUTURE FARMERS OF AMERICA PROGRAM.",
  "from_organization": "~{\"classification\": \"lower\"}",
  "classification": [
    "concurrent resolution"
  ],
  "subject": [
    "CTAHR",
    "DOE",
    "FFA",
    "Funding",
    "Position",
    "Secondary Agricultural Education Program",
    "UH"
  ],
  "abstracts": [],
  "other_titles": [],
  "other_identifiers": [
    {
      "identifier": "ocd-bill-hi-2026-hcr77"
    }
  ],
  "actions": [
    {
      "description": "Referred to HED/EDN, referral sheet 18",
      "date": "2026-03-18",
      "organization_id": "~{\"classification\": \"lower\"}",
      "classification": [
        "referral-committee"
      ],
      "related_entities": [
        {
          "name": "Higher Education",
          "entity_type": "organization",
          "organization_id": null
        },
        {
          "name": "Education",
          "entity_type": "organization",
          "organization_id": null
        }
      ],
      "_processing": {
        "log_file_created": "2026-07-13T06:04:02Z"
      }
    },
    {
      "description": "Offered",
      "date": "2026-03-16",
      "organization_id": "~{\"classification\": \"lower\"}",
      "classification": [
        "introduction"
      ],
      "related_entities": [],
      "_processing": {
        "log_file_created": "2026-07-13T06:04:02Z"
      }
    },
    {
      "description": "To be offered.",
      "date": "2026-03-12",
      "organization_id": "~{\"classification\": \"lower\"}",
      "classification": [],
      "related_entities": [],
      "_processing": {
        "log_file_created": "2026-07-13T06:04:02Z"
      }
    }
  ],
  "sponsorships": [
    {
      "name": "CHUN",
      "classification": "primary",
      "entity_type": "person",
      "primary": true,
      "person_id": "~{\"name\": \"CHUN\"}",
      "organization_id": null
    }
  ],
  "related_bills": [
    {
      "identifier": "HR 71, SCR134",
      "legislative_session": "2026 Regular Session",
      "relation_type": "companion"
    }
  ],
  "versions": [
    {
      "note": "HCR77",
      "links": [
        {
          "url": "https://data.capitol.hawaii.gov/sessions/session2026/bills/HCR77_.HTM",
          "media_type": "text/html"
        },
        {
          "url": "https://data.capitol.hawaii.gov/sessions/session2026/bills/HCR77_.PDF",
          "media_type": "application/pdf"
        }
      ],
      "date": "",
      "classification": ""
    }
  ],
  "documents": [],
  "citations": [],
  "sources": [
    {
      "url": "https://capitol.hawaii.gov/session/measure_indiv.aspx?billtype=HCR&billnumber=77&year=2026",
      "note": ""
    }
  ],
  "extras": {
    "current_referral": "HED/EDN"
  },
  "jurisdiction": {
    "id": "ocd-jurisdiction/country:us/state:hi/government",
    "name": "Hawaii",
    "classification": "state",
    "division_id": "ocd-division/country:us/state:hi"
  },
  "_processing": {
    "logs_latest_update": "2026-07-13T06:04:02Z"
  }
}