{
  "legislative_session": "2026",
  "identifier": "HB2420",
  "title": "RELATING TO THE JUDICIARY.",
  "from_organization": "~{\"classification\": \"lower\"}",
  "classification": [
    "bill"
  ],
  "subject": [
    "Appropriation ($)",
    "Community-based Organizations",
    "Judiciary"
  ],
  "abstracts": [
    {
      "note": "description",
      "abstract": "Appropriates funds to the judiciary for services contracted with community-based organizations that deliver essential services, streamline judicial processes, and support the judiciary's capacity to effectively meet the needs of vulnerable households."
    }
  ],
  "other_titles": [],
  "other_identifiers": [
    {
      "identifier": "ocd-bill-hi-2026-hb2420"
    }
  ],
  "actions": [
    {
      "description": "Referred to JHA, FIN, referral sheet 6",
      "date": "2026-02-02",
      "organization_id": "~{\"classification\": \"lower\"}",
      "classification": [
        "referral-committee"
      ],
      "related_entities": [
        {
          "name": "Judiciary & Hawaiian Affairs",
          "entity_type": "organization",
          "organization_id": null
        },
        {
          "name": "Finance",
          "entity_type": "organization",
          "organization_id": null
        }
      ],
      "_processing": {
        "log_file_created": "2026-07-13T06:04:06Z"
      }
    },
    {
      "description": "Introduced and Pass First Reading.",
      "date": "2026-01-28",
      "organization_id": "~{\"classification\": \"lower\"}",
      "classification": [
        "introduction",
        "reading-1"
      ],
      "related_entities": [],
      "_processing": {
        "log_file_created": "2026-07-13T06:04:06Z"
      }
    },
    {
      "description": "Pending introduction.",
      "date": "2026-01-27",
      "organization_id": "~{\"classification\": \"lower\"}",
      "classification": [],
      "related_entities": [],
      "_processing": {
        "log_file_created": "2026-07-13T06:04:06Z"
      }
    }
  ],
  "sponsorships": [
    {
      "name": "HARTSFIELD",
      "classification": "primary",
      "entity_type": "person",
      "primary": true,
      "person_id": "~{\"name\": \"HARTSFIELD\"}",
      "organization_id": null
    },
    {
      "name": "CHUN",
      "classification": "primary",
      "entity_type": "person",
      "primary": true,
      "person_id": "~{\"name\": \"CHUN\"}",
      "organization_id": null
    },
    {
      "name": "EVSLIN",
      "classification": "primary",
      "entity_type": "person",
      "primary": true,
      "person_id": "~{\"name\": \"EVSLIN\"}",
      "organization_id": null
    },
    {
      "name": "GARRETT",
      "classification": "primary",
      "entity_type": "person",
      "primary": true,
      "person_id": "~{\"name\": \"GARRETT\"}",
      "organization_id": null
    },
    {
      "name": "KAHALOA",
      "classification": "primary",
      "entity_type": "person",
      "primary": true,
      "person_id": "~{\"name\": \"KAHALOA\"}",
      "organization_id": null
    },
    {
      "name": "KILA",
      "classification": "primary",
      "entity_type": "person",
      "primary": true,
      "person_id": "~{\"name\": \"KILA\"}",
      "organization_id": null
    },
    {
      "name": "MIYAKE",
      "classification": "primary",
      "entity_type": "person",
      "primary": true,
      "person_id": "~{\"name\": \"MIYAKE\"}",
      "organization_id": null
    },
    {
      "name": "POEPOE",
      "classification": "primary",
      "entity_type": "person",
      "primary": true,
      "person_id": "~{\"name\": \"POEPOE\"}",
      "organization_id": null
    },
    {
      "name": "TAKENOUCHI",
      "classification": "primary",
      "entity_type": "person",
      "primary": true,
      "person_id": "~{\"name\": \"TAKENOUCHI\"}",
      "organization_id": null
    }
  ],
  "related_bills": [],
  "versions": [
    {
      "note": "HB2420",
      "links": [
        {
          "url": "https://data.capitol.hawaii.gov/sessions/session2026/bills/HB2420_.HTM",
          "media_type": "text/html"
        },
        {
          "url": "https://data.capitol.hawaii.gov/sessions/session2026/bills/HB2420_.PDF",
          "media_type": "application/pdf"
        }
      ],
      "date": "",
      "classification": ""
    }
  ],
  "documents": [],
  "citations": [],
  "sources": [
    {
      "url": "https://capitol.hawaii.gov/session/measure_indiv.aspx?billtype=HB&billnumber=2420&year=2026",
      "note": ""
    }
  ],
  "extras": {
    "current_referral": "JHA, FIN"
  },
  "jurisdiction": {
    "id": "ocd-jurisdiction/country:us/state:hi/government",
    "name": "Hawaii",
    "classification": "state",
    "division_id": "ocd-division/country:us/state:hi"
  },
  "_processing": {
    "logs_latest_update": "2026-07-13T06:04:06Z",
    "text_extraction_latest_update": "2026-07-13T10:01:46.849332Z"
  }
}