{
  "action": {
    "description": "Act 058, on 05/28/2026 (Gov. Msg. No. 1158).",
    "occurred_at": "2026-05-28",
    "jurisdiction_id": "~{\"classification\": \"lower\"}",
    "session_id": "2026",
    "entity_type": "bill",
    "classifications": [
      "became-law"
    ],
    "related_entities": [],
    "sources": [
      {
        "url": "https://capitol.hawaii.gov/session/measure_indiv.aspx?billtype=SB&billnumber=2818&year=2026",
        "note": ""
      }
    ]
  },
  "bill_id": "SB2818"
}