{
  "action": {
    "description": "Conference committee meeting scheduled for 04-22-25 10:40AM; Conference Room 329.",
    "occurred_at": "2025-04-21",
    "jurisdiction_id": "~{\"classification\": \"upper\"}",
    "session_id": "2026",
    "entity_type": "bill",
    "classifications": [],
    "related_entities": [],
    "sources": [
      {
        "url": "https://capitol.hawaii.gov/session/measure_indiv.aspx?billtype=SB&billnumber=1667&year=2026",
        "note": ""
      }
    ]
  },
  "bill_id": "SB1667"
}