{
  "action": {
    "description": "The committee on JHA recommend that the measure be PASSED, WITH AMENDMENTS. The votes were as follows: 7 Ayes: Representative(s) Tarnas, Poepoe, Kahaloa, Takayama; Ayes with reservations: Representative(s) Cochran, Garcia, Shimizu;  Noes: none; and 3 Excused: Representative(s) Belatti, Hashem, Sayama.",
    "occurred_at": "2026-03-05",
    "jurisdiction_id": "~{\"classification\": \"lower\"}",
    "session_id": "2026",
    "entity_type": "bill",
    "classifications": [
      "committee-passage-favorable"
    ],
    "related_entities": [],
    "sources": [
      {
        "url": "https://capitol.hawaii.gov/session/measure_indiv.aspx?billtype=HB&billnumber=1692&year=2026",
        "note": ""
      }
    ]
  },
  "bill_id": "HB1692"
}