{
  "action": {
    "description": "The committee on HSG recommend that the measure be PASSED, WITH AMENDMENTS. The votes were as follows: 6 Ayes: Representative(s) Evslin, Miyake, Grandinetti, Kila, Kitagawa, Muraoka; Ayes with reservations: none;  Noes: none; and 3 Excused: Representative(s) Cochran, La Chica, Pierick.",
    "occurred_at": "2025-02-05",
    "jurisdiction_id": "~{\"classification\": \"lower\"}",
    "session_id": "2026",
    "entity_type": "bill",
    "classifications": [
      "committee-passage-favorable"
    ],
    "related_entities": [],
    "sources": [
      {
        "url": "https://capitol.hawaii.gov/session/measure_indiv.aspx?billtype=HB&billnumber=528&year=2026",
        "note": ""
      }
    ]
  },
  "bill_id": "HB528"
}