{
  "legislative_session": "2026",
  "identifier": "SB2322",
  "title": "RELATING TO ENVIRONMENTAL ASSESSMENTS.",
  "from_organization": "~{\"classification\": \"upper\"}",
  "classification": [
    "bill"
  ],
  "subject": [
    "Environmental Assessment",
    "Environmental Impact Statement",
    "Requirement",
    "Significant Historic Properties",
    "Traditional Cultural Properties or Places"
  ],
  "abstracts": [
    {
      "note": "description",
      "abstract": "Requires that an environmental assessment be conducted and an environmental impact statement be prepared for any proposed use within historic properties designated by the Hawaii or National Register of Historic Places, important to native Hawaiian people or to another ethnic group of the State, or determined to be eligible as a traditional cultural property or place on the National Register of Historic Places.  Effective 7/1/2050.  (SD1)"
    }
  ],
  "other_titles": [],
  "other_identifiers": [
    {
      "identifier": "ocd-bill-hi-2026-sb2322"
    }
  ],
  "actions": [
    {
      "description": "Referred to EEP, WAL, JHA, referral sheet 17",
      "date": "2026-03-12",
      "organization_id": "~{\"classification\": \"lower\"}",
      "classification": [
        "referral-committee"
      ],
      "related_entities": [
        {
          "name": "Energy & Environmental Protection",
          "entity_type": "organization",
          "organization_id": null
        },
        {
          "name": "Water & Land",
          "entity_type": "organization",
          "organization_id": null
        },
        {
          "name": "Judiciary & Hawaiian Affairs",
          "entity_type": "organization",
          "organization_id": null
        }
      ],
      "_processing": {
        "log_file_created": "2026-07-13T06:04:08Z"
      }
    },
    {
      "description": "Pass First Reading",
      "date": "2026-03-12",
      "organization_id": "~{\"classification\": \"lower\"}",
      "classification": [
        "reading-1"
      ],
      "related_entities": [],
      "_processing": {
        "log_file_created": "2026-07-13T06:04:08Z"
      }
    },
    {
      "description": "Received from Senate (Sen. Com. No. 210) in amended form (SD 1).",
      "date": "2026-03-10",
      "organization_id": "~{\"classification\": \"lower\"}",
      "classification": [
        "introduction",
        "receipt"
      ],
      "related_entities": [],
      "_processing": {
        "log_file_created": "2026-07-13T06:04:08Z"
      }
    },
    {
      "description": "Report adopted; Passed Third Reading.  Ayes, 25; Aye(s) with reservations: none .  Noes, 0 (none). Excused, 0 (none).  Transmitted to House.",
      "date": "2026-03-10",
      "organization_id": "~{\"classification\": \"upper\"}",
      "classification": [
        "passage"
      ],
      "related_entities": [],
      "_processing": {
        "log_file_created": "2026-07-13T06:04:08Z"
      }
    },
    {
      "description": "One Day Notice 03-10-26.",
      "date": "2026-03-06",
      "organization_id": "~{\"classification\": \"upper\"}",
      "classification": [],
      "related_entities": [],
      "_processing": {
        "log_file_created": "2026-07-13T06:04:08Z"
      }
    },
    {
      "description": "Reported from JDC (Stand. Com. Rep. No. 2985) with recommendation of passage on Third Reading.",
      "date": "2026-03-06",
      "organization_id": "~{\"classification\": \"upper\"}",
      "classification": [],
      "related_entities": [],
      "_processing": {
        "log_file_created": "2026-07-13T06:04:08Z"
      }
    },
    {
      "description": "The committee(s) on JDC recommend(s) that the measure be PASSED, UNAMENDED.  The votes in JDC were as follows: 5 Aye(s): Senator(s) Rhoads, Gabbard, Chang, San Buenaventura, Awa; Aye(s) with reservations: none ; 0 No(es): none; and 0 Excused: none.",
      "date": "2026-02-27",
      "organization_id": "~{\"classification\": \"upper\"}",
      "classification": [
        "committee-passage-favorable"
      ],
      "related_entities": [],
      "_processing": {
        "log_file_created": "2026-07-13T06:04:08Z"
      }
    },
    {
      "description": "The committee(s) on JDC will hold a public decision making on 02-27-26 10:30AM; Conference Room 016 & Videoconference.",
      "date": "2026-02-23",
      "organization_id": "~{\"classification\": \"upper\"}",
      "classification": [],
      "related_entities": [],
      "_processing": {
        "log_file_created": "2026-07-13T06:04:08Z"
      }
    },
    {
      "description": "Report adopted; Passed Second Reading, as amended (SD 1) and referred to JDC.",
      "date": "2026-02-20",
      "organization_id": "~{\"classification\": \"upper\"}",
      "classification": [
        "reading-2",
        "referral-committee"
      ],
      "related_entities": [
        {
          "name": "Judiciary",
          "entity_type": "organization",
          "organization_id": null
        }
      ],
      "_processing": {
        "log_file_created": "2026-07-13T06:04:08Z"
      }
    },
    {
      "description": "Reported from WLA/AEN (Stand. Com. Rep. No. 2620) with recommendation of passage on Second Reading, as amended (SD 1) and referral to JDC.",
      "date": "2026-02-20",
      "organization_id": "~{\"classification\": \"upper\"}",
      "classification": [],
      "related_entities": [],
      "_processing": {
        "log_file_created": "2026-07-13T06:04:08Z"
      }
    },
    {
      "description": "The committee(s) on  WLA recommend(s) that the measure be PASSED, WITH AMENDMENTS.  The votes in WLA were as follows: 5 Aye(s): Senator(s) Lee, C., Inouye, Chang, Lamosao, DeCorte; Aye(s) with reservations: none ; 0 No(es): none; and 0 Excused: none.",
      "date": "2026-02-11",
      "organization_id": "~{\"classification\": \"upper\"}",
      "classification": [
        "committee-passage-favorable"
      ],
      "related_entities": [],
      "_processing": {
        "log_file_created": "2026-07-13T06:04:08Z"
      }
    },
    {
      "description": "The committee(s) on  AEN recommend(s) that the measure be PASSED, WITH AMENDMENTS.  The votes in AEN were as follows: 5 Aye(s): Senator(s) Gabbard, Richards, DeCoite, Rhoads, Awa; Aye(s) with reservations: none ; 0 No(es): none; and 0 Excused: none.",
      "date": "2026-02-11",
      "organization_id": "~{\"classification\": \"upper\"}",
      "classification": [
        "committee-passage-favorable"
      ],
      "related_entities": [],
      "_processing": {
        "log_file_created": "2026-07-13T06:04:08Z"
      }
    },
    {
      "description": "The committee(s) on WLA/AEN has scheduled a public hearing on 02-11-26 1:00PM; CR 224 & Videoconference.",
      "date": "2026-02-06",
      "organization_id": "~{\"classification\": \"upper\"}",
      "classification": [],
      "related_entities": [],
      "_processing": {
        "log_file_created": "2026-07-13T06:04:08Z"
      }
    },
    {
      "description": "Referred to WLA/AEN, JDC.",
      "date": "2026-01-26",
      "organization_id": "~{\"classification\": \"upper\"}",
      "classification": [
        "referral-committee"
      ],
      "related_entities": [
        {
          "name": "Water, Land, Culture and the Arts",
          "entity_type": "organization",
          "organization_id": null
        },
        {
          "name": "Agriculture and Environment",
          "entity_type": "organization",
          "organization_id": null
        },
        {
          "name": "Judiciary",
          "entity_type": "organization",
          "organization_id": null
        }
      ],
      "_processing": {
        "log_file_created": "2026-07-13T06:04:08Z"
      }
    },
    {
      "description": "Introduced and passed First Reading.",
      "date": "2026-01-21",
      "organization_id": "~{\"classification\": \"upper\"}",
      "classification": [
        "introduction"
      ],
      "related_entities": [],
      "_processing": {
        "log_file_created": "2026-07-13T06:04:08Z"
      }
    },
    {
      "description": "Pending Introduction.",
      "date": "2026-01-15",
      "organization_id": "~{\"classification\": \"upper\"}",
      "classification": [],
      "related_entities": [],
      "_processing": {
        "log_file_created": "2026-07-13T06:04:08Z"
      }
    }
  ],
  "sponsorships": [
    {
      "name": "GABBARD",
      "classification": "primary",
      "entity_type": "person",
      "primary": true,
      "person_id": "~{\"name\": \"GABBARD\"}",
      "organization_id": null
    },
    {
      "name": "San Buenaventura",
      "classification": "cosponsor",
      "entity_type": "person",
      "primary": false,
      "person_id": "~{\"name\": \"San Buenaventura\"}",
      "organization_id": null
    }
  ],
  "related_bills": [
    {
      "identifier": "HB 1544",
      "legislative_session": "2026 Regular Session",
      "relation_type": "companion"
    }
  ],
  "versions": [
    {
      "note": "SB2322_SD1",
      "links": [
        {
          "url": "https://data.capitol.hawaii.gov/sessions/session2026/bills/SB2322_SD1_.HTM",
          "media_type": "text/html"
        },
        {
          "url": "https://data.capitol.hawaii.gov/sessions/session2026/bills/SB2322_SD1_.PDF",
          "media_type": "application/pdf"
        }
      ],
      "date": "",
      "classification": ""
    },
    {
      "note": "SB2322",
      "links": [
        {
          "url": "https://data.capitol.hawaii.gov/sessions/session2026/bills/SB2322_.HTM",
          "media_type": "text/html"
        },
        {
          "url": "https://data.capitol.hawaii.gov/sessions/session2026/bills/SB2322_.PDF",
          "media_type": "application/pdf"
        }
      ],
      "date": "",
      "classification": ""
    }
  ],
  "documents": [],
  "citations": [],
  "sources": [
    {
      "url": "https://capitol.hawaii.gov/session/measure_indiv.aspx?billtype=SB&billnumber=2322&year=2026",
      "note": ""
    }
  ],
  "extras": {
    "current_referral": "EEP, WAL, JHA"
  },
  "jurisdiction": {
    "id": "ocd-jurisdiction/country:us/state:hi/government",
    "name": "Hawaii",
    "classification": "state",
    "division_id": "ocd-division/country:us/state:hi"
  },
  "_processing": {
    "logs_latest_update": "2026-07-13T06:04:08Z",
    "text_extraction_latest_update": "2026-07-13T10:59:55.291203Z"
  }
}