{
  "action": {
    "description": "The committee(s) on WAM/JDC will hold a public decision making on 04-01-25 10:00AM; Conference Room 211 & Videoconference.",
    "occurred_at": "2025-03-27",
    "jurisdiction_id": "~{\"classification\": \"upper\"}",
    "session_id": "2026",
    "entity_type": "bill",
    "classifications": [],
    "related_entities": [],
    "sources": [
      {
        "url": "https://capitol.hawaii.gov/session/measure_indiv.aspx?billtype=HB&billnumber=697&year=2026",
        "note": ""
      }
    ]
  },
  "bill_id": "HB697"
}