{
  "action": {
    "description": "The committee(s) on LBT recommend(s) that the measure be PASSED, UNAMENDED.  The votes in LBT were as follows: 4 Aye(s): Senator(s) Elefante, Lamosao, Ihara; Aye(s) with reservations: Senator(s) Moriwaki ; 0 No(es): none; and 1 Excused: Senator(s) Fevella.",
    "occurred_at": "2026-03-16",
    "jurisdiction_id": "~{\"classification\": \"upper\"}",
    "session_id": "2026",
    "entity_type": "bill",
    "classifications": [
      "committee-passage-favorable"
    ],
    "related_entities": [],
    "sources": [
      {
        "url": "https://capitol.hawaii.gov/session/measure_indiv.aspx?billtype=HB&billnumber=1658&year=2026",
        "note": ""
      }
    ]
  },
  "bill_id": "HB1658"
}