{
  "action": {
    "description": "Received from Senate (Sen. Com. No. 132) in amended form (SD 1).",
    "occurred_at": "2026-03-06",
    "jurisdiction_id": "~{\"classification\": \"lower\"}",
    "session_id": "2026",
    "entity_type": "bill",
    "classifications": [
      "introduction",
      "receipt"
    ],
    "related_entities": [],
    "sources": [
      {
        "url": "https://capitol.hawaii.gov/session/measure_indiv.aspx?billtype=SB&billnumber=3286&year=2026",
        "note": ""
      }
    ]
  },
  "bill_id": "SB3286"
}