{
  "action": {
    "description": "The committee on EDN recommend that the measure be PASSED, UNAMENDED. The votes were as follows: 9 Ayes: Representative(s) Woodson, La Chica, Evslin, Garrett, Kapela, Kila, Souza; Ayes with reservations: Representative(s) Amato, Olds; 1 Noes: Representative(s) Muraoka; and 0 Excused: none.",
    "occurred_at": "2026-02-19",
    "jurisdiction_id": "~{\"classification\": \"lower\"}",
    "session_id": "2026",
    "entity_type": "bill",
    "classifications": [
      "committee-passage-favorable"
    ],
    "related_entities": [],
    "sources": [
      {
        "url": "https://capitol.hawaii.gov/session/measure_indiv.aspx?billtype=HB&billnumber=1937&year=2026",
        "note": ""
      }
    ]
  },
  "bill_id": "HB1937"
}