{
  "action": {
    "description": "Act 008, 04/28/2026 (Gov. Msg. No. 1108).",
    "occurred_at": "2026-04-29",
    "jurisdiction_id": "~{\"classification\": \"upper\"}",
    "session_id": "2026",
    "entity_type": "bill",
    "classifications": [
      "became-law"
    ],
    "related_entities": [],
    "sources": [
      {
        "url": "https://capitol.hawaii.gov/session/measure_indiv.aspx?billtype=HB&billnumber=2099&year=2026",
        "note": ""
      }
    ]
  },
  "bill_id": "HB2099"
}